pyre/__init__.py
pyre/__main__.py
pyre_tools-1.5.0.dist-info/licenses/LICENSE
pyre_tools-1.5.0.dist-info/METADATA
pyre_tools-1.5.0.dist-info/WHEEL
pyre_tools-1.5.0.dist-info/entry_points.txt
pyre_tools-1.5.0.dist-info/top_level.txt
pyre_tools-1.5.0.dist-info/RECORD
