Metadata-Version: 2.4
Name: pyre_tools
Version: 1.5.0
Summary: 从源文件中提取Python项目依赖项的CLI工具。
Home-page: https://github.com/dawalishi122/pypre_tools
Author: dawalishi122
Author-email: 1710802268@qq.com
License: MIT
Classifier: Programming Language :: Python :: 3
Classifier: Operating System :: OS Independent
Requires-Python: >=3.6
License-File: LICENSE
Dynamic: author
Dynamic: author-email
Dynamic: classifier
Dynamic: description
Dynamic: description-content-type
Dynamic: home-page
Dynamic: license
Dynamic: license-file
Dynamic: requires-python
Dynamic: summary
